groupme_push/__init__.py
groupme_push/client.py
groupme_push-0.0.3.dist-info/LICENSE
groupme_push-0.0.3.dist-info/METADATA
groupme_push-0.0.3.dist-info/WHEEL
groupme_push-0.0.3.dist-info/top_level.txt
groupme_push-0.0.3.dist-info/RECORD
