Metadata-Version: 2.1
Name: groupme-push
Version: 0.0.3
Summary: GroupMe push service wrapper
Author-email: Chris Cush <chris@cuuush.com>
License: GPL-3.0-or-later
Project-URL: Homepage, https://github.com/cuuush/groupme-push
Keywords: groupme,push,websocket
Requires-Python: >=3.9
License-File: LICENSE
Requires-Dist: base36 >=0.1.1
Requires-Dist: requests ~=2.31.0
Requires-Dist: websocket-client >=1.7.0
